layeutils/__init__.py
layeutils/ai.py
layeutils/dataprocess.py
layeutils/date.py
layeutils/directus.py
layeutils/dtale.py
layeutils/googlesheets.py
layeutils/image.py
layeutils/mongodb.py
layeutils/obsidian.py
layeutils/plotly.py
layeutils/request.py
layeutils/telegram.py
layeutils/video.py
layeutils-0.2.57.dist-info/LICENSE
layeutils-0.2.57.dist-info/METADATA
layeutils-0.2.57.dist-info/WHEEL
layeutils-0.2.57.dist-info/top_level.txt
layeutils-0.2.57.dist-info/RECORD
