Metadata-Version: 2.1
Name: layeutils
Version: 0.2.57
Summary: Private Utils
Author: LayeWang
Author-email: laye0619@gmail.com
Classifier: Programming Language :: Python :: 3
Classifier: License :: OSI Approved :: MIT License
Classifier: Operating System :: OS Independent
License-File: LICENSE
